setup.cfg
setup.py
multimple/__init__.py
multimple.egg-info/PKG-INFO
multimple.egg-info/SOURCES.txt
multimple.egg-info/dependency_links.txt
multimple.egg-info/top_level.txt