Metadata-Version: 1.0
Name: multimple
Version: 0.0
Summary: Multiple implementations to your Python classes
Home-page: UNKNOWN
Author: Bagrat Aznauryan
Author-email: bagrat@aznauryan.org
License: UNKNOWN
Platform: UNKNOWN
